{
  "Total" : {
    "transaction" : "Total",
    "sampleCount" : 4,
    "errorCount" : 0,
    "errorPct" : 0.0,
    "meanResTime" : 52.0,
    "medianResTime" : 55.0,
    "minResTime" : 33.0,
    "maxResTime" : 65.0,
    "pct1ResTime" : 65.0,
    "pct2ResTime" : 65.0,
    "pct3ResTime" : 65.0,
    "throughput" : 0.0673548082913769,
    "receivedKBytesPerSec" : 0.0,
    "sentKBytesPerSec" : 0.0
  },
  "CPU_localhost" : {
    "transaction" : "CPU_localhost",
    "sampleCount" : 4,
    "errorCount" : 0,
    "errorPct" : 0.0,
    "meanResTime" : 52.0,
    "medianResTime" : 55.0,
    "minResTime" : 33.0,
    "maxResTime" : 65.0,
    "pct1ResTime" : 65.0,
    "pct2ResTime" : 65.0,
    "pct3ResTime" : 65.0,
    "throughput" : 0.0673548082913769,
    "receivedKBytesPerSec" : 0.0,
    "sentKBytesPerSec" : 0.0
  }
}